odoo/addons/account_force_early_discount/README.rst
odoo/addons/account_force_early_discount/__init__.py
odoo/addons/account_force_early_discount/__manifest__.py
odoo/addons/account_force_early_discount/i18n/account_force_early_discount.pot
odoo/addons/account_force_early_discount/i18n/it.po
odoo/addons/account_force_early_discount/models/__init__.py
odoo/addons/account_force_early_discount/models/account_move.py
odoo/addons/account_force_early_discount/readme/CONTRIBUTORS.md
odoo/addons/account_force_early_discount/readme/DESCRIPTION.md
odoo/addons/account_force_early_discount/readme/USAGE.md
odoo/addons/account_force_early_discount/static/description/icon.png
odoo/addons/account_force_early_discount/static/description/index.html
odoo/addons/account_force_early_discount/tests/__init__.py
odoo/addons/account_force_early_discount/tests/common.py
odoo/addons/account_force_early_discount/tests/test_financial_discount_manual_payment.py
odoo/addons/account_force_early_discount/views/account_move.xml
odoo/addons/account_force_early_discount/wizard/__init__.py
odoo/addons/account_force_early_discount/wizard/account_payment_register.py
odoo/addons/account_force_early_discount/wizard/account_payment_register.xml
odoo_addon_account_force_early_discount-18.0.1.0.0.5.dist-info/METADATA
odoo_addon_account_force_early_discount-18.0.1.0.0.5.dist-info/WHEEL
odoo_addon_account_force_early_discount-18.0.1.0.0.5.dist-info/top_level.txt
odoo_addon_account_force_early_discount-18.0.1.0.0.5.dist-info/RECORD
